solrvalidator/__init__.py
solrvalidator/src/__init__.py
solrvalidator/src/validator.py
solrvalidator-0.1.11.dist-info/METADATA
solrvalidator-0.1.11.dist-info/WHEEL
solrvalidator-0.1.11.dist-info/top_level.txt
solrvalidator-0.1.11.dist-info/RECORD
