Metadata-Version: 2.1
Name: solrvalidator
Version: 0.1.11
Summary: validation
Author: nxbz44
Author-email: nxbz44@yopmail.com
